{
  "personalInfo": {
    "name": "Ahmed Hassanen",
    "title": "Senior Frontend Engineer",
    "profileImage": "/assets/profile.png",
    "bio": "I'm a passionate developer with a knack for creating beautiful, functional, and accessible web experiences. I love tackling complex problems and turning ideas into reality. This portfolio is a showcase of my journey in tech.",
    "email": "alex.doe@example.com",
    "github": "https://github.com/example",
    "linkedin": "https://linkedin.com/in/example",
    "whatsapp1": "1234567890",
    "whatsapp2": "0987654321",
    "phone1": "1234567890",
    "phone2": "0987654321",
    "credly": "https://www.credly.com/users/username",
    "googleSkills": "https://www.google.com/profiles/skills/username",
    "coursera": "https://www.coursera.org/user/username"
  },
  "files": {
    "bgvidUrl1": "/assets/bg-vid-1.mp4",
    "bgvidUrl2": "/assets/bg-vid-2.mp4",
    "pdfUrl": "/assets/resumes/Ahmed-Hassanen.pdf",
    "wordUrl": "/assets/resumes/Ahmed-Hassanen.docx"
  },
  "aboutme":{
    "description": "Experienced Frontend Engineer with a demonstrated history of working in the information technology and services industry. Skilled in React, TypeScript, JavaScript (ES6+), Node.js, HTML5 & CSS3. Strong engineering professional with a Bachelor's degree focused in Computer Science from University of Technology.",
    "Languages": [
      {
        "name": "English",
        "proficiency": "Native or Bilingual Proficiency"
      },
      {
        "name": "Arabic",
        "proficiency": "Native or Bilingual Proficiency"
      }
    ],
    "Availability": "Immediate",
    "Location": "Dubai, UAE",
    "PreferredLocations": "UAE, Saudi Arabia, Qatar, Remote",
    "Relocation": "Open to relocate anywhere"
  },
  "experience": [
    {
      "company": "Tech Solutions Inc.",
      "title": "Senior Frontend Engineer",
      "period": "Jan 2020 - Present",
      "description": "Led the development of a new user-facing analytics dashboard using React and D3.js. Mentored junior developers and improved code quality across the team by implementing a new style guide."
    },
    {
      "company": "Web Innovators",
      "title": "Frontend Developer",
      "period": "Jun 2017 - Dec 2019",
      "description": "Developed and maintained responsive websites for various clients using HTML, CSS, and JavaScript. Collaborated with designers to ensure pixel-perfect implementation of UIs."
    }
  ],
  "education": [
    {
      "institution": "University of Technology",
      "degree": "Bachelor of Science in Computer Science",
      "period": "Sep 2013 - May 2017",
      "description": "Graduated with honors. Focused on software engineering and web development principles. Participated in the annual coding competition."
    }
  ],
  "skills": {
    "Programming Languages": [
      "React",
      "TypeScript",
      "JavaScript (ES6+)",
      "Node.js",
      "HTML5 & CSS3"
    ],
    "Tools & Technologies": [
      "Webpack",
      "Vite",
      "Git & GitHub",
      "Jest & RTL"
    ],
    "Industry Knowledge": [
      "UI/UX Design",
      "Accessibility",
      "Agile Methodologies"
    ],
    "Interpersonal Skills": [
      "Team Leadership",
      "Mentoring",
      "Communication"
    ]
  },
  "projects": [
    {
      "name": "Project Alpha",
      "description": "A full-stack web application for project management, built with React and Node.js.",
      "link": "https://github.com/example/project-alpha"
    },
    {
      "name": "Portfolio Website",
      "description": "This very portfolio, built to be easily configurable and deployable.",
      "link": "https://github.com/example/portfolio"
    }
  ],
  "certificates": {
    "Cloud, DevOps, & IT Service Management": [ {
        "name": "UI/UX Design Specialization",
        "link": "https://www.coursera.org/specializations/ui-ux-design",
        "provider": "Coursera",
        "dateObtained": "2023-08-15",
        "expiryDate": "2025-08-15"
      }],
    "Atlassian Technical Expertise": [],
    "Cyber Security": [],
    "Web Development & Design": [
      {
        "name": "Advanced React",
        "link": "https://scrimba.com/learn/advancedreact",
        "provider": "Scrimba",
        "dateObtained": "2023-08-15",
        "expiryDate": ""
      },
      {
        "name": "UI/UX Design Specialization",
        "link": "https://www.coursera.org/specializations/ui-ux-design",
        "provider": "Coursera",
        "dateObtained": "2023-08-15",
        "expiryDate": ""
      }, 
      {
        "name": "UI/UX Design SpecializationSpecializationSpecialization",
        "link": "https://www.coursera.org/specializations/ui-ux-design",
        "provider": "Coursera",
        "dateObtained": "2023-08-15",
        "expiryDate": ""
      }
    ]
  },
  "badges": {
    "Cloud, DevOps, & IT Service Management": [{
        "name": "GitHub Arctic Code Vault Contributor",
        "imageUrl": "https://images.credly.com/size/110x110/images/00634f82-b07f-4bbd-a6bb-53de397fc3a6/image.png",
        "link": "https://images.credly.com/size/110x110/images/00634f82-b07f-4bbd-a6bb-53de397fc3a6/image.png",
        "skills": "React, TypeScript, JavaScript (ES6+), Node.js, HTML5 & CSS3"
      }],
    "Atlassian Technical Expertise": [],
    "Cyber Security": [],
    "Web Development & Design": [{
        "name": "GitHub Contributor",
        "imageUrl": "https://images.credly.com/size/110x110/images/00634f82-b07f-4bbd-a6bb-53de397fc3a6/image.png",
        "link": "https://images.credly.com/size/110x110/images/00634f82-b07f-4bbd-a6bb-53de397fc3a6/image.png",
        "skills": "React, TypeScript, JavaScript (ES6+), Node.js, HTML5 & CSS3"
      },
      {
        "name": "AWS Certified Cloud Practitioner",
        "imageUrl": "https://images.credly.com/size/110x110/images/00634f82-b07f-4bbd-a6bb-53de397fc3a6/image.png",
        "link": "https://images.credly.com/size/110x110/images/00634f82-b07f-4bbd-a6bb-53de397fc3a6/image.png",
        "skills": "UI/UX Design, Accessibility, Agile Methodologies"
      }
    ]
  }
}